<?xml version="1.0" encoding="utf-8"?>
<Root>
	<Entry>
		<zType/>
		<Translation/>
	</Entry>
	<Entry>
		<zType>TEXT_GAME_LOST_TEAM_ALLIANCE</zType>
		<Translation>Ya no eres aliado de {0_team}.</Translation>
	</Entry>
	<Entry>
		<zType>TEXT_GAME_GAINED_TEAM_ALLIANCE</zType>
		<Translation>Ahora eres aliado de {0_team}.</Translation>
	</Entry>
	<Entry>
		<zType>TEXT_GAME_LOST_TRIBE_ALLIANCE</zType>
		<Translation>Ya no estás aliado con los {0_barbarians}.</Translation>
	</Entry>
	<Entry>
		<zType>TEXT_GAME_GAINED_TRIBE_ALLIANCE</zType>
		<Translation>Ahora estás aliado con los {0_barbarians}.</Translation>
	</Entry>
	<Entry>
		<zType>TEXT_GAME_MET_TRIBE</zType>
		<Translation>Has conocido a los {0_barbarians}</Translation>
	</Entry>
	<Entry>
		<zType>TEXT_GAME_TRIBE_NEW_DIPLOMACY</zType>
		<Translation>{0_team} está {1_newDiplomacy} con los {2_barbarians}.</Translation>
	</Entry>
	<Entry>
		<zType>TEXT_GAME_TRIBE_DIPLOMACY_LOG_DATA</zType>
		<Translation>{0_barbarians}: {1_newDiplomacy}</Translation>
	</Entry>
	<Entry>
		<zType>TEXT_GAME_UNIT_COMBAT_EFFECT_LOG_DATA</zType>
		<Translation>¡{0_character} ahora és {1_trait} por combatir!</Translation>
	</Entry>
	<Entry>
		<zType>TEXT_GAME_TEAM_CONTACT_LOG_DATA</zType>
		<Translation>Has conocido a {0_team}</Translation>
	</Entry>
	<Entry>
		<zType>TEXT_GAME_TEAM_NEW_DIPLOMACY</zType>
		<Translation>{0_team} está {1_newDiplomacy} con {2_team}.</Translation>
	</Entry>
	<Entry>
		<zType>TEXT_GAME_TEAM_DIPLOMACY_LOG_DATA</zType>
		<Translation>{0_team}: {1_newDiplomacy}</Translation>
	</Entry>
	<Entry>
		<zType>TEXT_GAME_TEAM_ALLIANCE_WAR</zType>
		<Translation>**Because of an link(CONCEPT_ALLIANCE_PLAYER) with {0_team}, {1_player} responds to the link(DIPLOMACY_WAR) Declaration by {2_team} with link(DIPLOMACY_WAR)!</Translation>
	</Entry>
	<Entry>
		<zType>TEXT_GAME_TRIBE_ALLIANCE_WAR</zType>
		<Translation>**Because of an link(CONCEPT_ALLIANCE_TRIBE) with {0_team}, {1_tribe} responds to the link(DIPLOMACY_WAR) Declaration by {2_team} with link(DIPLOMACY_WAR)!</Translation>
	</Entry>
	<Entry>
		<zType>TEXT_GAME_RELIGION_THEOLOGY</zType>
		<Translation>Se ha establecido {1_theology} en el {0_religion}.</Translation>
	</Entry>
	<Entry>
		<zType>TEXT_GAME_GAME_OVER_POPUP</zType>
		<Translation>Has llegado al final de la partida.</Translation>
	</Entry>
	<Entry>
		<zType>TEXT_GAME_TEAM_DEFEAT_POPUP</zType>
		<Translation>¡La nación de {0_player} ha sido eliminada!</Translation>
	</Entry>
	<Entry>
		<zType>TEXT_GAME_TEAM_DEFEAT_POPUP_NO_HEIR</zType>
		<Translation>¡La dinastía real de {0_player} ha llegado a su fin!</Translation>
	</Entry>
	<Entry>
		<zType>TEXT_GAME_PLAYER_SURRENDER_POPUP</zType>
		<Translation>¡{0_player} se ha rendido!</Translation>
	</Entry>
	<Entry>
		<zType>TEXT_GAME_RELIGION_FOUNDED</zType>
		<Translation>¡Se ha fundado el {0_religion} en {1_city}!</Translation>
	</Entry>
	<Entry>
		<zType>TEXT_GAME_RELIGION_HEAD</zType>
		<Translation><![CDATA[¡{0_character} és ahora el <masculine_0>el máximo<feminine>la máxima<end> representante del {1_religion}!]]></Translation>
	</Entry>
	<Entry>
		<zType>TEXT_GAME_RELIGION_FAMILY</zType>
		<Translation>¡La familia {0_family} se ha convertido al {1_religion}!</Translation>
	</Entry>
	<Entry>
		<zType>TEXT_GAME_RELIGION_TRIBE</zType>
		<Translation>¡Los {0_tribe} se han convertido al {1_religion}!</Translation>
	</Entry>
	<Entry>
		<zType>TEXT_GAME_FAMILY_HEAD</zType>
		<Translation><![CDATA[¡{0_character} és ahora el <masculine_0>el máximo<feminine>la máxima<end> representante de la familia {1_family}!]]></Translation>
	</Entry>
	<Entry>
		<zType>TEXT_GAME_IMPROVEMENT_STARTED</zType>
		<Translation>¡{0_player} ha comenzado la construcción de {1_improvement}!</Translation>
	</Entry>
	<Entry>
		<zType>TEXT_GAME_IMPROVEMENT_COMPLETED</zType>
		<Translation>¡{1_player} ha completado {0_improvement}!</Translation>
	</Entry>
	<Entry>
		<zType>TEXT_GAME_RELIGION_SPREAD_TO_CITY</zType>
		<Translation>El {0_religion} se expande a {1_city}</Translation>
	</Entry>
	<Entry>
		<zType>TEXT_GAME_DOOMED_POPUP</zType>
		<Translation>Los médicos y adivinos te advierten que tu final se acerca. Es hora de poner todos los asuntos pendientes en orden.</Translation>
	</Entry>
	<Entry>
		<zType>TEXT_GAME_OTHER_TEAM_NEW_RULER_POPUP</zType>
		<Translation>Han llegado noticias que {0_oldLeader} ha muerto. Un nuevo dirigente, {1_newLeader}, ha tomado el trono.</Translation>
	</Entry>
	<Entry>
		<zType>TEXT_GAME_TRIBE_NEW_RULER_POPUP</zType>
		<Translation>Han llegado noticias que {0_oldLeader} ha muerto. {1_newLeader} ahora lidera a los {2_tribe}.</Translation>
	</Entry>
	<Entry>
		<zType>TEXT_GAME_NEW_LAW_FOR_HEIR_POPUP</zType>
		<Translation>No tienes ningún heredero legítimo según la ley de sucessión actual. Se ha cambiado a {0_law} para permitir la ascensión de {1_character}.</Translation>
	</Entry>
	<Entry>
		<zType>TEXT_GAME_START_AMBITION</zType>
		<Translation>{0_character} tiene una nueva ambición: {1_ambition}</Translation>
	</Entry>
	<Entry>
		<zType>TEXT_GAME_START_AMBITION_DESIRED</zType>
		<Translation>{0_character} está persiguiendo su ambición: {1_ambition}</Translation>
	</Entry>
	<Entry>
		<zType>TEXT_GAME_START_QUEST</zType>
		<Translation><![CDATA[has empezado una tarea: {0} <true_1>(en {1} turnos)<false><end>]]></Translation>
	</Entry>
	<Entry>
		<zType>TEXT_GAME_FINISH_AMBITION</zType>
		<Translation>Has completado una Ambición: {0}</Translation>
	</Entry>
	<Entry>
		<zType>TEXT_GAME_FINISH_LEGACY</zType>
		<Translation>Has completado un Legado: {0}</Translation>
	</Entry>
	<Entry>
		<zType>TEXT_GAME_FINISH_QUEST</zType>
		<Translation>Has completado una Tarea: {0}</Translation>
	</Entry>
	<Entry>
		<zType>TEXT_GAME_FAIL_AMBITION</zType>
		<Translation>Has fracasado en {true_1:una Legado:una Ambición}: {0}</Translation>
	</Entry>
	<Entry>
		<zType>TEXT_GAME_FAIL_QUEST</zType>
		<Translation>Has fracasado en una Tarea: {0}</Translation>
	</Entry>
	<Entry>
		<zType>TEXT_GAME_AMBITION_IMPOSSIBLE</zType>
		<Translation>{true_1:Este Legado:Esta Ambición} ahora es imposible y ha sido {true_1:eliminado:eliminada}: {0}</Translation>
	</Entry>
	<Entry>
		<zType>TEXT_GAME_QUEST_IMPOSSIBLE</zType>
		<Translation>Esta tarea ahora es imposible y ha sido eliminada: {0}</Translation>
	</Entry>
	<Entry>
		<zType>TEXT_GAME_BARBARIAN_WAVE_COMING_POPUP</zType>
		<Translation>Tus centinelas informan que una oleada de link(TRIBE_BARBARIANS,1) puede aparecer en los próximos años.</Translation>
	</Entry>
	<Entry>
		<zType>TEXT_GAME_COURTIER_JOINED_POPUP</zType>
		<Translation>{0_character} se ha incoporado a la corte!</Translation>
	</Entry>
	<Entry>
		<zType>TEXT_GAME_CHARACTER_ADULT_POPUP</zType>
		<Translation>¡{0_character} ya es adulto! ({1_age} años)</Translation>
	</Entry>
	<Entry>
		<zType>TEXT_GAME_CHARACTER_DESIRED_AMBITION</zType>
		<Translation>{0_character} tiene una nueva ambición: {1_goal}</Translation>
	</Entry>
	<Entry>
		<zType>TEXT_GAME_CHARACTER_CHOOSES_RELIGION</zType>
		<Translation>{0_character} se ha convertido al {1_religion}</Translation>
	</Entry>
	<Entry>
		<zType>TEXT_GAME_COVER_DEBTS_LOG_DATA</zType>
		<Translation>¡Se han vendido {0_goodsList} para saldar las deudas!</Translation>
	</Entry>
	<Entry>
		<zType>TEXT_GAME_SHORTFALL_LOG_DATA</zType>
		<Translation>Se ha ejecutado {0_project} en {1_city} para evitar un déficit de {2_yield}.</Translation>
	</Entry>
	<Entry>
		<zType>TEXT_GAME_QUEUED_BUILD_BUY_GOODS_LOG_DATA</zType>
		<Translation>Acción en cola: Pagar {0_money} para comprar {1_yields} ({2_improvement})</Translation>
	</Entry>
	<Entry>
		<zType>TEXT_GAME_FOUNDED_CITY_LOG_DATA</zType>
		<Translation>Se ha establecido {0_city}</Translation>
	</Entry>
	<Entry>
		<zType>TEXT_GAME_DISCOVERED_TECH_LOG_DATA</zType>
		<Translation>Has descubierto {0_tech}</Translation>
	</Entry>
	<Entry>
		<zType>TEXT_GAME_CITY_FINISHED_PROJECT_LOG_DATA</zType>
		<Translation>{0_city} ha finalizado un link(CONCEPT_PROJECT_INFO): {1_project}</Translation>
	</Entry>
	<Entry>
		<zType>TEXT_GAME_CITY_DEVELOPED_SPECIALIST_LOG_DATA</zType>
		<Translation>{0_city} ha formado {1,1_specialist}</Translation>
	</Entry>
	<Entry>
		<zType>TEXT_GAME_CITY_TRAINED_UNIT_LOG_DATA</zType>
		<Translation>{0_city} ha entrenado {1,1_unit}</Translation>
	</Entry>
	<Entry>
		<zType>TEXT_GAME_CHARACTER_GAINS_TRAIT</zType>
		<Translation>¡{0_character} ahora es {1_trait}!</Translation>
	</Entry>
	<Entry>
		<zType>TEXT_GAME_CHARACTER_LOSES_TRAIT</zType>
		<Translation>¡{0_character} ya no es {1_trait}!</Translation>
	</Entry>
	<Entry>
		<zType>TEXT_GAME_CHARACTER_RATING_CHANGE</zType>
		<Translation>{0_character}: {1_value} {2_rating}</Translation>
	</Entry>
	<Entry>
		<zType>TEXT_GAME_CHARACTER_ACQUIRES_TRAIT</zType>
		<Translation>¡{0_character} tiene un nuevo rasgo: {1_trait}!</Translation>
	</Entry>
	<Entry>
		<zType>TEXT_GAME_LANDMARK_DISCOVERED</zType>
		<Translation>¡Lugar de referencia descubierto: {0_name}!</Translation>
	</Entry>
	<Entry>
		<zType>TEXT_GAME_LANDMARK_NAMED</zType>
		<Translation><![CDATA[Eres el primero en descubrir este lugar.<br>¿Cómo lo llamarías?]]></Translation>
	</Entry>
	<Entry>
		<zType>TEXT_GAME_RAID_WARNING</zType>
		<Translation>¡Informes sobre una incursión de los {0,2_tribe} {1_improvement} cerca de {2_city}!</Translation>
	</Entry>
	<Entry>
		<zType>TEXT_GAME_GIVE_BIRTH_LOG_DATA</zType>
		<Translation>¡{0_childName} ha nacido!</Translation>
	</Entry>
	<Entry>
		<zType>TEXT_GAME_GIVE_BIRTH_LEADER</zType>
		<Translation><![CDATA[¡<true_0>Has<false>Tu esposa ha<end> dado a luz a <masculine_1>un hijo<feminine>una hija<end>, {1_childName}!]]></Translation>
	</Entry>
	<Entry>
		<zType>TEXT_GAME_GIVE_BIRTH_LEADER_ILLEGITIMATE</zType>
		<Translation><![CDATA[<comment variable 0 is the leader i.e. "you" for gender purposes for foreign languages>¡Tienes <masculine_1>un hijo ilegítimo<feminine>una hija ilegítima<end>, {1_childName}!]]></Translation>
	</Entry>
	<Entry>
		<zType>TEXT_GAME_GIVE_BIRTH_NON_LEADER</zType>
		<Translation><![CDATA[¡{0_father} y {1_mother} han tenido <masculine_2>un hijo<feminine>una hija<end>, {2_childName}!]]></Translation>
	</Entry>
	<Entry>
		<zType>TEXT_GAME_GIVE_BIRTH_NON_LEADER_ILLEGITIMATE</zType>
		<Translation><![CDATA[¡{0_father} han tenido <masculine_1>un hijo ilegítimo<feminine>una hija ilegítima<end>, {1_childName}!]]></Translation>
	</Entry>
	<Entry>
		<zType>TEXT_GAME_EVENT_CITY_LOG_DATA</zType>
		<Translation>{0_event} en {1_city}</Translation>
	</Entry>
	<Entry>
		<zType>TEXT_GAME_TEAM</zType>
		<Translation>Equipo {0_teamNum}</Translation>
	</Entry>
	<!--Decisions-->
	<Entry>
		<zType>TEXT_GAME_DECISION_RETIRING_GENERAL_TITLE</zType>
		<Translation>Jubilación de un link(CONCEPT_GENERAL)</Translation>
	</Entry>
	<Entry>
		<zType>TEXT_GAME_DECISION_RETIRING_GENERAL</zType>
		<Translation>{0_character}, link(CONCEPT_GENERAL) de {1_unit} és muy viejo y se retira del campo de batalla.</Translation>
	</Entry>
	<Entry>
		<zType>TEXT_GAME_DECISION_RETIRING_GENERAL_PROMPT</zType>
		<Translation>Elije un nuevo link(CONCEPT_GENERAL)</Translation>
	</Entry>
	<Entry>
		<zType>TEXT_GAME_DECISION_DEAD_COUNCIL_TITLE</zType>
		<Translation>Un {0_council} ha muerto</Translation>
	</Entry>
	<Entry>
		<zType>TEXT_GAME_DECISION_DEAD_COUNCIL</zType>
		<Translation>{0_character}, nuestro {1_council}, ha muerto.</Translation>
	</Entry>
	<Entry>
		<zType>TEXT_GAME_DECISION_DEAD_COUNCIL_PROMPT</zType>
		<Translation>Elije un nuevo {0_council}</Translation>
	</Entry>
	<Entry>
		<zType>TEXT_GAME_DECISION_DEAD_GOVERNOR_TITLE</zType>
		<Translation>Un link(CONCEPT_GOVERNOR) ha muerto</Translation>
	</Entry>
	<Entry>
		<zType>TEXT_GAME_DECISION_DEAD_GOVERNOR</zType>
		<Translation>{0_character}, link(CONCEPT_GOVERNOR) de {1_city} ha muerto.</Translation>
	</Entry>
	<Entry>
		<zType>TEXT_GAME_DECISION_DEAD_GOVERNOR_PROMPT</zType>
		<Translation>Elije un nuevo link(CONCEPT_GOVERNOR)</Translation>
	</Entry>
	<!--Do Bonus-->
	<Entry>
		<zType>TEXT_GAME_DO_BONUS_MEMORY_ALL_PLAYERS</zType>
		<Translation>Todas las naciones de {0_player}: {1_memory}, {2_value} de Opinión</Translation>
	</Entry>
	<Entry>
		<zType>TEXT_GAME_DO_BONUS_MEMORY_ALL_FAMILIES</zType>
		<Translation>Todas las familias: {0_memory}, {1_value} de Opinión</Translation>
	</Entry>
	<Entry>
		<zType>TEXT_GAME_DO_BONUS_MEMORY_SUBJECT</zType>
		<Translation>{0_subject}: {1_memory}, {2_value} de Opinión</Translation>
	</Entry>
	<Entry>
		<zType>TEXT_GAME_DO_BONUS_FORGET_SUBJECT</zType>
		<Translation>{0_subject}: Olvida {1_memory}, {2_value} de Opinión</Translation>
	</Entry>
	<Entry>
		<zType>TEXT_GAME_DO_BONUS_END_ALLIANCE</zType>
		<Translation>Fin de la {0_alliance} con {1_subject}</Translation>
	</Entry>
	<Entry>
		<zType>TEXT_GAME_DO_BONUS_DIPLOMACY_WITH_PLAYER</zType>
		<Translation>En {0_diplomacy} con {1_player}</Translation>
	</Entry>
	<Entry>
		<zType>TEXT_GAME_DO_BONUS_ALLIANCE_WITH</zType>
		<Translation>{0_player} en alianza con {1_other}</Translation>
	</Entry>
	<Entry>
		<zType>TEXT_GAME_DO_BONUS_OTHER_PLAYER</zType>
		<Translation>Recibes {0_yield} de {1_player}</Translation>
	</Entry>
	<Entry>
		<zType>TEXT_GAME_DO_BONUS_SEND_PLAYER</zType>
		<Translation>Envias {0_yield} a {1_player}</Translation>
	</Entry>
	<Entry>
		<zType>TEXT_GAME_DO_BONUS_TRADE_PLAYER</zType>
		<Translation>{0_trade} **Trade with {1_player}</Translation>
	</Entry>
	<Entry>
		<zType>TEXT_GAME_DO_BONUS_TRIBUTE_PLAYER</zType>
		<Translation>{0_tribute} **Tribute with {1_player}</Translation>
	</Entry>
	<Entry>
		<zType>TEXT_GAME_DO_BONUS_OTHER_PLAYER_DIPLOMACY</zType>
		<Translation>{0_other} está en {1_diplomacy} con {2_target}</Translation>
	</Entry>
	<Entry>
		<zType>TEXT_GAME_DO_BONUS_DIPLOMACY_TRIBE</zType>
		<Translation>Estás en {0_diplomacy} con los {1_barbarian}</Translation>
	</Entry>
	<Entry>
		<zType>TEXT_GAME_DO_BONUS_TRIBUTE_TRIBE</zType>
		<Translation>{0_tribute} *Tribute with {1_barbarian}</Translation>
	</Entry>
	<Entry>
		<zType>TEXT_GAME_DO_BONUS_TRIBE_DIPLOMACY_PLAYER</zType>
		<Translation>{0_barbarian}: Está en {1_diplomacy} con {2_player}</Translation>
	</Entry>
	<Entry>
		<zType>TEXT_GAME_DO_BONUS_ADOPT_RELIGION</zType>
		<Translation>Adopta el {0_religion} como Religión Estatal</Translation>
	</Entry>
	<Entry>
		<zType>TEXT_GAME_DO_BONUS_SPREAD_RELIGION</zType>
		<Translation>El {0_religion} se expande a {1_city}</Translation>
	</Entry>
	<Entry>
		<zType>TEXT_GAME_DO_BONUS_REMOVE_RELIGION</zType>
		<Translation>El {0_religion} desaparece de {1_city}</Translation>
	</Entry>
	<Entry>
		<zType>TEXT_GAME_DO_BONUS_CONVERT_RELIGION</zType>
		<Translation>{0_character} se convierte al {1_religion}</Translation>
	</Entry>
	<Entry>
		<zType>TEXT_GAME_DO_BONUS_HEAD_RELIGION</zType>
		<Translation><![CDATA[{0_character} és ahora <masculine_0>el máximo<feminine>la máxima<end> representante del {1_religion}]]></Translation>
	</Entry>
	<Entry>
		<zType>TEXT_GAME_DO_BONUS_FAMILY_LAW</zType>
		<Translation>{0_family}: {1_law} Opinión {2_value}</Translation>
	</Entry>
	<Entry>
		<zType>TEXT_GAME_DO_BONUS_START_LAW</zType>
		<Translation>Inicio de {0_law}</Translation>
	</Entry>
	<Entry>
		<zType>TEXT_GAME_DO_BONUS_FREE_LAW</zType>
		<Translation>{0_law} gratuita</Translation>
	</Entry>
	<Entry>
		<zType>TEXT_GAME_DO_BONUS_FREE_THEOLOGY</zType>
		<Translation>{0_theology} gratuita ({1_religion})</Translation>
	</Entry>
	<Entry>
		<zType>TEXT_GAME_DO_BONUS_FOUND_RELIGION_CITY</zType>
		<Translation>Establecer el {0_religion}</Translation>
	</Entry>
	<Entry>
		<zType>TEXT_GAME_DO_BONUS_CITIZENS</zType>
		<Translation><![CDATA[{0_value} <singular_0>{1_citizenLink}<plural>{1,2_citizenLink}<end>]]></Translation>
	</Entry>
	<Entry>
		<zType>TEXT_GAME_DO_BONUS_BORDER_GROWTH</zType>
		<Translation><![CDATA[{0_value} <singular_0>Casilla fronteriza<plural>Casillas fronterizas<end>]]></Translation>
	</Entry>
	<Entry>
		<zType>TEXT_GAME_DO_BONUS_CULTURE_LEVELS</zType>
		<Translation><![CDATA[{0_value} <singular_0>{1_culture}<plural>{1,2_culture}<end>]]></Translation>
	</Entry>
	<Entry>
		<zType>TEXT_GAME_DO_BONUS_DISCONTENT_LEVELS</zType>
		<Translation><![CDATA[{0_value} <singular_0>Nivel<plural>Niveles<end> de link(YIELD_DISCONTENT)]]></Translation>
	</Entry>
	<Entry>
		<zType>TEXT_GAME_DO_BONUS_REBEL_UNITS</zType>
		<Translation><![CDATA[{0_value} <singular_0>Unidad<plural>Unidades<end> {1_rebel}]]></Translation>
	</Entry>
	<Entry>
		<zType>TEXT_GAME_DO_BONUS_IMPROVEMENTS_DESTROYED</zType>
		<Translation><![CDATA[{0_value} <singular_0>Mejora<plural>Mejoras<end> destruidas]]></Translation>
	</Entry>
	<Entry>
		<zType>TEXT_GAME_DO_BONUS_HP</zType>
		<Translation>{0_damage} PS</Translation>
	</Entry>
	<Entry>
		<zType>TEXT_GAME_DO_BONUS_AGENT_CITY</zType>
		<Translation>{0_character} se convierte en link(CONCEPT_AGENT)</Translation>
	</Entry>
	<Entry>
		<zType>TEXT_GAME_DO_BONUS_PLUS_ONE</zType>
		<Translation>+1 {0}</Translation>
	</Entry>
	<Entry>
		<zType>TEXT_GAME_DO_BONUS_MINUS_ONE</zType>
		<Translation>-1 {0}</Translation>
	</Entry>
	<Entry>
		<zType>TEXT_GAME_DO_BONUS_MEMORY_CHARACTER</zType>
		<Translation>{0_memory}, {1_value} Opinión</Translation>
	</Entry>
	<Entry>
		<zType>TEXT_GAME_DO_BONUS_FORGET_CHARACTER</zType>
		<Translation>Olvida {0_memory}, {1_value} Opinión</Translation>
	</Entry>
	<Entry>
		<zType>TEXT_DO_BONUS_DESIRED_AMBITION</zType>
		<Translation>Desea {0}</Translation>
	</Entry>
	<Entry>
		<zType>TEXT_GAME_DO_BONUS_RANDOM_TRAIT</zType>
		<Translation>{0_character} es {1_trait}</Translation>
	</Entry>
	<Entry>
		<zType>TEXT_GAME_DO_BONUS_RANDOM_RELATIONSHIP_LEADER</zType>
		<Translation>{0_character} ahora es {1_relationship} de {2_leader}</Translation>
	</Entry>
	<Entry>
		<zType>TEXT_GAME_DO_BONUS_GAINS</zType>
		<Translation>Se convierte en {0}</Translation>
	</Entry>
	<Entry>
		<zType>TEXT_GAME_DO_BONUS_LOSES</zType>
		<Translation>Ya no es {0}</Translation>
	</Entry>
	<Entry>
		<zType>TEXT_GAME_DO_BONUS_STARTS_MISSION</zType>
		<Translation>{0_character} empieza una misión: {1_mission}</Translation>
	</Entry>
	<Entry>
		<zType>TEXT_GAME_DO_BONUS_VICTORY</zType>
		<Translation>{0_victory} **Victoria</Translation>
	</Entry>
	<Entry>
		<zType>TEXT_GAME_DO_BONUS_ADD_COURTIER_OTHER</zType>
		<Translation>{0,1_player} {1_courtier}</Translation>
	</Entry>
	<Entry>
		<zType>TEXT_GAME_DO_BONUS_PLAYER_START_LAW</zType>
		<Translation>{0_player}: Inicia {1_law}</Translation>
	</Entry>
	<Entry>
		<zType>TEXT_GAME_DO_BONUS_PLAYER_END_LAW</zType>
		<Translation>{0_player}: Finaliza {1_law}</Translation>
	</Entry>
	<Entry>
		<zType>TEXT_GAME_DO_BONUS_PLAYER_FREE_LAW</zType>
		<Translation>{0_player}: {1_law} gratuita</Translation>
	</Entry>
	<Entry>
		<zType>TEXT_GAME_DO_BONUS_LEAVE_COURT</zType>
		<Translation>Deja la corte</Translation>
	</Entry>
	<Entry>
		<zType>TEXT_GAME_DO_BONUS_LEAVE_COUNCIL</zType>
		<Translation>Renuncia como {0_council}</Translation>
	</Entry>
	<Entry>
		<zType>TEXT_GAME_DO_BONUS_MAKE_GOVERNOR</zType>
		<Translation>link(CONCEPT_GOVERNOR) de {0_city}</Translation>
	</Entry>
	<Entry>
		<zType>TEXT_GAME_DO_BONUS_MAKE_GENERAL</zType>
		<Translation>link(CONCEPT_GENERAL) de {0_unit}</Translation>
	</Entry>
	<Entry>
		<zType>TEXT_GAME_DO_BONUS_SEIZE_THRONE</zType>
		<Translation>Líder de {0_player}</Translation>
	</Entry>
	<Entry>
		<zType>TEXT_GAME_DO_BONUS_ADOPTION</zType>
		<Translation>Adoptado por {0_parent}</Translation>
	</Entry>
	<Entry>
		<zType>TEXT_GAME_DO_BONUS_MARRIES</zType>
		<Translation>Se casa con {0_suitor}</Translation>
	</Entry>
	<Entry>
		<zType>TEXT_GAME_DO_BONUS_DIVORCES</zType>
		<Translation>Se divorcia de {0_spouse}</Translation>
	</Entry>
	<Entry>
		<zType>TEXT_GAME_DO_BONUS_BIRTH_WITH</zType>
		<Translation><![CDATA[¡{0_father} Tiene <masculine_1>un hijo<feminine>una hija<end> con {0_parent}]]></Translation>
	</Entry>
	<Entry>
		<zType>TEXT_GAME_DO_BONUS_ABDICATES</zType>
		<Translation>Abdica</Translation>
	</Entry>
	<Entry>
		<zType>TEXT_GAME_DO_BONUS_CHOSEN_HEIR</zType>
		<Translation>Es el heredero elegido</Translation>
	</Entry>
	<Entry>
		<zType>TEXT_GAME_DO_BONUS_KILL_CHARACTER</zType>
		<Translation>Muere</Translation>
	</Entry>
	<Entry>
		<zType>TEXT_GAME_DO_BONUS_HAS_ILLEGITIMATE_CHILD</zType>
		<Translation><![CDATA[¡{0_father} Tiene <masculine_1>un hijo ilegítimo<feminine>una hija ilegítima<end> con {0_parent}]]></Translation>
	</Entry>
	<Entry>
		<zType>TEXT_GAME_DO_BONUS_RELATIONSHIP_ADD</zType>
		<Translation>Estará {0_relationship} de {1_character}</Translation>
	</Entry>
	<Entry>
		<zType>TEXT_GAME_DO_BONUS_RELATIONSHIP_ADD_REMOVE</zType>
		<Translation>{0} (**Elimina {1_list})</Translation>
	</Entry>
	<Entry>
		<zType>TEXT_GAME_DO_BONUS_RELATIONSHIP_REMOVE</zType>
		<Translation>Ya no está {0_relationship} {1_character}</Translation>
	</Entry>
	<Entry>
		<zType>TEXT_GAME_DO_BONUS_XP</zType>
		<Translation>{0_value} PX</Translation>
	</Entry>
	<Entry>
		<zType>TEXT_GAME_DO_BONUS_KILL_UNIT</zType>
		<Translation>Muere</Translation>
	</Entry>
	<Entry>
		<zType>TEXT_GAME_DO_BONUS_REVEAL_RANGE</zType>
		<Translation><![CDATA[Descubre <singular_0>la casilla<plural>todas las casillas<end> a {0_dist} de distancia]]></Translation>
	</Entry>
	<Entry>
		<zType>TEXT_GAME_DO_BONUS_SET_VEGETATION</zType>
		<Translation>Coloca {0_vegetation} en {1_tile}</Translation>
	</Entry>
	<Entry>
		<zType>TEXT_GAME_DO_BONUS_SET_RESOURCE</zType>
		<Translation>Coloca {0_resource} en {1_tile}</Translation>
	</Entry>
	<Entry>
		<zType>TEXT_GAME_DO_BONUS_SET_IMPROVEMENT</zType>
		<Translation>Coloca {0_improvement} en {1_tile}</Translation>
	</Entry>
	<Entry>
		<zType>TEXT_GAME_DO_BONUS_REMOVE_VEGETATION</zType>
		<Translation>Elimina {0_vegetation} de {1_tile}</Translation>
	</Entry>
	<Entry>
		<zType>TEXT_GAME_DO_BONUS_TRIBE_RAID</zType>
		<Translation>Incursión de los {0,1_barbarian} {1_improvement} desde {2_tile}</Translation>
	</Entry>
	<Entry>
		<zType>TEXT_GAME_DO_BONUS_PLAYER_ADOPT_RELIGION</zType>
		<Translation>{0_player}: Adopta el {1_religion} como Religión Estatal</Translation>
	</Entry>
	<Entry>
		<zType>TEXT_GAME_DO_BONUS_PLAYER_FREE_THEOLOGY</zType>
		<Translation>{0_player}: {1_theology} gratuita ({2_religion})</Translation>
	</Entry>
	<Entry>
		<zType>TEXT_GAME_DO_BONUS_HOLY_CITY_AGENTS</zType>
		<Translation>{0_player}: link(CONCEPT_AGENT) gratuito en todas las Ciudades Santas</Translation>
	</Entry>
	<Entry>
		<zType>TEXT_GAME_DO_BONUS_FOUND_RELIGION</zType>
		<Translation>{0_player}: Funda el {1_religion}</Translation>
	</Entry>
	<Entry>
		<zType>TEXT_GAME_DO_BONUS_STATE_RELIGION_END</zType>
		<Translation>{0_player}: Finaliza la Religión Estatal ({1_religion})</Translation>
	</Entry>
	<Entry>
		<zType>TEXT_GAME_DO_BONUS_TECH</zType>
		<Translation>{0_player}: {1_tech} (Tecnología)</Translation>
	</Entry>
	<Entry>
		<zType>TEXT_GAME_POPUP_BONUS_TECH</zType>
		<Translation>{0_player} descubre una nueva tecnología: {1_tech}.</Translation>
	</Entry>
	<Entry>
		<zType>TEXT_GAME_DO_BONUS_LOG_DATA</zType>
		<Translation>**De {0}: </Translation>
	</Entry>
	<Entry>
		<zType>TEXT_GAME_CHARACTER_FINISHED_MISSION</zType>
		<Translation>{0_character} ha finalizado {1_mission}</Translation>
	</Entry>
	<Entry>
		<zType>TEXT_GAME_CHARACTER_MISSION_NO_EFFECT</zType>
		<Translation>{0_character}: {1_mission} no tiene ningún efecto</Translation>
	</Entry>
	<Entry>
		<zType>TEXT_GAME_UNIT_ATTACK_CRITICAL</zType>
		<Translation>¡Crítico! </Translation>
	</Entry>
	<Entry>
		<zType>TEXT_GAME_UNIT_ATTACK_DAMAGE</zType>
		<Translation>¡-{0_damage} PS!</Translation>
	</Entry>
	<Entry>
		<zType>TEXT_GAME_CITY_ATTACKED_LOG_DATA</zType>
		<Translation>¡{0_city} ha sido atacada!</Translation>
	</Entry>
	<Entry>
		<zType>TEXT_GAME_CAMP_DESTROYED_LOG_DATA</zType>
		<Translation>¡{1_improvement} {0_barbarian} destruido!</Translation>
	</Entry>
	<Entry>
		<zType>TEXT_GAME_CITY_CAPTURED_LOG_DATA</zType>
		<Translation>{0_city} capturada por {1_player}</Translation>
	</Entry>
	<Entry>
		<zType>TEXT_GAME_CITY_WE_CAPTURED_LOG_DATA</zType>
		<Translation>Has capturado {0_city} de {1_player}</Translation>
	</Entry>
	<Entry>
		<zType>TEXT_GAME_CITY_CANCEL_BUILD_LOG_DATA</zType>
		<Translation>{0_build} cancelado en {1_city}</Translation>
	</Entry>
	<Entry>
		<zType>TEXT_GAME_CITY_DISCONTENT_CHANGE_LOG_DATA</zType>
		<Translation><![CDATA[{0_level} <singular_0>nivel<plural>niveles<end> de link(YIELD_DISCONTENT) en {1_city}]]></Translation>
	</Entry>
	<Entry>
		<zType>TEXT_GAME_UNIT_ATTACKED_LOG_DATA</zType>
		<Translation>¡{0_unit} ha sido atacado!</Translation>
	</Entry>
	<Entry>
		<zType>TEXT_GAME_UNIT_KILLED</zType>
		<Translation>¡{0_unit} eliminada!</Translation>
	</Entry>
	<Entry>
		<zType>TEXT_GAME_UNIT_SEEN</zType>
		<Translation>¡{0_unit} hostiles divisados!</Translation>
	</Entry>
	<Entry>
		<zType>TEXT_GAME_UNIT_MOVE_CANCELLED</zType>
		<Translation>{0_unit} ha cancelado el automovimiento</Translation>
	</Entry>
	<Entry>
		<zType>TEXT_GAME_LAUNCH_OFFENSIVE_LOG_DATA</zType>
		<Translation>¡{0_unit} lanza una ofesiva!</Translation>
	</Entry>
	<Entry>
		<zType>TEXT_GAME_UNIT_ESTABLISH_THEOLOGY_LOG_DATA</zType>
		<Translation>{2_player} establece {1_theology} ({0,1_religion}) en {3_city}!</Translation>
	</Entry>
	<!--Tile Renderer-->
	<Entry>
		<zType>TEXT_GAME_TILE_CITY_SITE</zType>
		<Translation>Emplazamiento</Translation>
	</Entry>
	<Entry>
		<zType>TEXT_GAME_TILE_UNREVEALED_SITE</zType>
		<Translation>Casilla oculta</Translation>
	</Entry>
	<Entry>
		<zType>TEXT_GAME_TILE_IMPROVEMENT_UPGRADE</zType>
		<Translation>({0_name}: {1_turns})</Translation>
	</Entry>
	<Entry>
		<zType>TEXT_GAME_UPLOADING_GAME_POPUP</zType>
		<Translation>Subiendo partida...</Translation>
	</Entry>
	<Entry>
		<zType>TEXT_GAME_NOT_CONNECTED_TO_ONLINE_SERVICES_POPUP</zType>
		<Translation>No estás conectado a los servicios en línea</Translation>
	</Entry>
	<Entry>
		<zType>TEXT_GAME_UPLOAD_COMPLETE_POPUP</zType>
		<Translation>La subida se ha completado</Translation>
	</Entry>
	<Entry>
		<zType>TEXT_GAME_UPLOAD_FAILED_POPUP</zType>
		<Translation>La subida ha fallado</Translation>
	</Entry>
	<Entry>
		<zType>TEXT_GAME_SAVED</zType>
		<Translation>Partida guardada</Translation>
	</Entry>
	<Entry>
		<zType>TEXT_GAME_FAILED_TO_SAVE</zType>
		<Translation>La partida no se ha podido guardar</Translation>
	</Entry>
	<Entry>
		<zType>TEXT_GAME_CHAT_ALL_TAG</zType>
		<Translation>**TODOS</Translation>
	</Entry>
	<Entry>
		<zType>TEXT_GAME_CHAT_TEAM_TAG</zType>
		<Translation>**EQUIPO</Translation>
	</Entry>
	<Entry>
		<zType>TEXT_GAME_CHAT_MESSAGE_FORMAT</zType>
		<Translation>{0_fromPlayer}[{1_tag}]: {2_msg}</Translation>
	</Entry>
	<Entry>
		<zType>TEXT_GAME_TILE_NOT_UNLIMBERED</zType>
		<Translation>**No liberada</Translation>
	</Entry>
	<!--Unit-->
	<Entry>
		<zType>TEXT_GAME_UNIT_TILE_DAMAGE</zType>
		<Translation>{0} PS</Translation>
	</Entry>
	<Entry>
		<zType>TEXT_GAME_UNIT_TILE_LEVEL_UP</zType>
		<Translation>¡Nivel {0}!</Translation>
	</Entry>
	<Entry>
		<zType>TEXT_GAME_UNIT_TILE_GAIN_XP</zType>
		<Translation>{0} PX</Translation>
	</Entry>
	<Entry>
		<zType>TEXT_GAME_UNIT_TILE_JOIN_CITY</zType>
		<Translation>{0} {1,2_citizenLink}</Translation>
	</Entry>
	<Entry>
		<zType>TEXT_GAME_UNIT_PILLAGED_IMPROVEMENT</zType>
		<Translation><![CDATA[¡{0} <masculine_1>saqueado<feminine>saqueado<end>!]]></Translation>
	</Entry>
	<Entry>
		<zType>TEXT_GAME_UNIT_FINISHED_CARAVAN_MISSION</zType>
		<Translation>link(CONCEPT_CARAVAN_MISSION) con {0_player} completada: {1_money}</Translation>
	</Entry>
	<!--City-->
	<Entry>
		<zType>TEXT_GAME_CITY_YIELD_FROM_CULTURE_EVENT</zType>
		<Translation>##De link(CONCEPT_CULTURE_EVENT): {0}</Translation>
	</Entry>
	<Entry>
		<zType>TEXT_GAME_CITY_REBEL_UNITS_NEAR_CITY</zType>
		<Translation>¡Los link(TRIBE_REBELS) han entrenado un {0_unit} cerca de {1_city}!</Translation>
	</Entry>
	<Entry>
		<zType>TEXT_GAME_CITY_CURRY_POPULATION_CITIZENS_COST</zType>
		<Translation>{0} Ciudadanos</Translation>
	</Entry>
	<!--Player-->
	<Entry>
		<zType>TEXT_GAME_PLAYER_RESOURCE_SHORTFALL</zType>
		<Translation>En déficit: Gasta {0} para comprar {1}</Translation>
	</Entry>
	<Entry>
		<zType>TEXT_GAME_PLAYER_MISSION_CANCELLED</zType>
		<Translation>La misión de {0} ha sido cancelada: {1}</Translation>
	</Entry>
	<Entry>
		<zType>TEXT_GAME_PLAYER_YIELD_ORDERS_SOLD_FOR_YIELD</zType>
		<Translation>{0} vendidos por {1}</Translation>
	</Entry>
	<Entry>
		<zType>TEXT_GAME_PLAYER_YIELD_YIELD_CONVERTED_TO_ORDERS</zType>
		<Translation>{0} convertidos en {1}</Translation>
	</Entry>
	<Entry>
		<zType>TEXT_GAME_PLAYER_SAVE_AND_RELOAD_TO_PLAY_POPUP</zType>
		<Translation>No se ha encontrado el ID del usuario: Guarda y recarga para jugar como el siguiente jugador</Translation>
	</Entry>
	<Entry>
		<zType>TEXT_GAME_PLAYER_FAILED_TO_UPLOAD_TO_CLOUD_POPUP</zType>
		<Translation>Error al subir</Translation>
	</Entry>
	<Entry>
		<zType>TEXT_GAME_PLAYER_YIELD_GIFT_RECIEVED</zType>
		<Translation>¡Has recibido {0_amount} {1}!</Translation>
	</Entry>
	<Entry>
		<zType>TEXT_GAME_PLAYER_DECLARED_WAR_ON</zType>
		<Translation>Se ha declarado la guerra en {0_strength} {1}</Translation>
	</Entry>
	<Entry>
		<zType>TEXT_GAME_PLAYER_TRUCE_WITH</zType>
		<Translation>Se ha declarado una tregua con {0_strength} {1}</Translation>
	</Entry>
	<Entry>
		<zType>TEXT_GAME_PLAYER_AI_ORDERS_TO_TEAMMATES</zType>
		<Translation>{0_player} te regala {1} {2_yield} sin utilizar</Translation>
	</Entry>
</Root>
